tprdbreader/__init__.py
tprdbreader/readtprdb.py
tprdbreader-0.1.3.dist-info/LICENSE.txt
tprdbreader-0.1.3.dist-info/METADATA
tprdbreader-0.1.3.dist-info/WHEEL
tprdbreader-0.1.3.dist-info/top_level.txt
tprdbreader-0.1.3.dist-info/RECORD
