Metadata-Version: 2.2
Name: tprdbreader
Version: 0.1.3
Summary: A library to read Translation Process Research Database (TPR-DB) tables from Google Cloud Storage.
Author: Devisri
Author-email: bandarudevisri.ds@gmail.com
Classifier: Programming Language :: Python :: 3
Classifier: License :: OSI Approved :: MIT License
Classifier: Operating System :: OS Independent
Requires-Python: >=3.6
License-File: LICENSE.txt
Requires-Dist: pandas
Requires-Dist: google-cloud-storage
Dynamic: author
Dynamic: author-email
Dynamic: classifier
Dynamic: description
Dynamic: description-content-type
Dynamic: requires-dist
Dynamic: requires-python
Dynamic: summary
